LICENSE
tiktokpy/__init__.py
tiktokpy/bot/__init__.py
tiktokpy/bot/decorators.py
tiktokpy/bot/version.py
tiktokpy/cli/__init__.py
tiktokpy/cli/utils.py
tiktokpy/client/__init__.py
tiktokpy/client/login.py
tiktokpy/client/trending.py
tiktokpy/client/user.py
tiktokpy/models/__init__.py
tiktokpy/models/feed.py
tiktokpy/utils/__init__.py
tiktokpy/utils/client.py
tiktokpy/utils/logger.py
tiktokpy/utils/settings.py
tiktokpy-0.9.4.dist-info/LICENSE
tiktokpy-0.9.4.dist-info/METADATA
tiktokpy-0.9.4.dist-info/WHEEL
tiktokpy-0.9.4.dist-info/entry_points.txt
tiktokpy-0.9.4.dist-info/RECORD
