Metadata-Version: 2.1
Name: tiktokpy
Version: 0.9.4
Summary: Tool for automated TikTok interactions.
Home-page: https://github.com/sudoguy/tiktokpy/
License: MIT
Keywords: tiktok,bot,api,wrapper,tiktokbot,tiktokpy,webapi,marketing
Author: Evgeny Kemerov
Author-email: eskemerov@gmail.com
Requires-Python: >=3.8,<4.0
Classifier: Development Status :: 3 - Alpha
Classifier: Environment :: Console
Classifier: Intended Audience :: End Users/Desktop
Classifier: Intended Audience :: Information Technology
Classifier: Intended Audience :: Science/Research
Classifier: License :: OSI Approved :: MIT License
Classifier: Operating System :: OS Independent
Classifier: Programming Language :: Python :: 3
Classifier: Programming Language :: Python :: 3.8
Classifier: Programming Language :: Python :: 3.9
Classifier: Programming Language :: Python :: 3.10
Classifier: Programming Language :: Python :: 3.11
Classifier: Topic :: Software Development :: Libraries :: Python Modules
Provides-Extra: html
Requires-Dist: dynaconf (>=3.0.0,<4.0.0)
Requires-Dist: humanize (>=4.0.0,<5.0.0)
Requires-Dist: loguru (>=0.6.0,<0.7.0)
Requires-Dist: parsel (>=1.6.0,<2.0.0) ; extra == "html"
Requires-Dist: playwright (>=1.18.2,<2.0.0)
Requires-Dist: playwright-stealth (>=1.0.5,<2.0.0)
Requires-Dist: pydantic (>=1.6.1,<2.0.0)
Requires-Dist: tqdm (>=4.48.0,<5.0.0)
Requires-Dist: typer (>=0.9.0,<0.10.0)
Project-URL: Repository, https://github.com/sudoguy/tiktokpy/
